LICENSE
README.md
setup.py
src/pyaw.py
src/PyAviationWeather.egg-info/PKG-INFO
src/PyAviationWeather.egg-info/SOURCES.txt
src/PyAviationWeather.egg-info/dependency_links.txt
src/PyAviationWeather.egg-info/requires.txt
src/PyAviationWeather.egg-info/top_level.txt