Metadata-Version: 2.1
Name: PyAviationWeather
Version: 0.0.1
Summary: An aviation weather information python package
Home-page: UNKNOWN
Author: William Ng
Author-email: Williamntw.Website@gmail.com
License: UNKNOWN
Platform: UNKNOWN
Classifier: Programming Language :: Python :: 3
Classifier: License :: OSI Approved :: MIT License
Classifier: Operating System :: OS Independent
License-File: LICENSE
